{"elementList": [{"propertyCode": "33387025", "thumbnail": "https://img3.idealista.pt/blur/WEB_LISTING/0/id.pro.pt.image.master/d4/1e/68/243164225.jpg", "externalReference": "PF33361", "numPhotos": 31, "floor": "bj", "price": 1200000.0, "priceInfo": {"price": {"amount": 1200000.0}}, "propertyType": "duplex", "operation": "sale", "size": 213.0, "rooms": 2, "bathrooms": 4, "address": "Pedrou\u00e7os", "province": "Lisboa", "municipality": "Bel\u00e9m", "district": "Pedrou\u00e7os", "country": "pt", "latitude": 38.697372, "longitude": -9.2248369, "showAddress": false, "url": "https://www.idealista.pt/imovel/33387025/", "hasVideo": true, "status": "good", "newDevelopment": false, "hasLift": true, "priceByArea": 5634.0, "detailedType": {"typology": "flat", "subTypology": "duplex"}, "suggestedTexts": {"subtitle": "Bel\u00e9m, Lisboa", "title": "D\u00faplex"}, "hasPlan": false, "has3DTour": true, "has360": false, "hasStaging": false, "topNewDevelopment": false, "topPlus": false}, {"propertyCode": "33386964", "thumbnail": "https://img3.idealista.pt/blur/WEB_LISTING/0/id.pro.pt.image.master/c4/b6/b1/242331358.jpg", "externalReference": "SAV15112_6D \t", "numPhotos": 26, "floor": "6", "price": 680000.0, "priceInfo": {"price": {"amount": 680000.0}}, "propertyType": "flat", "operation": "sale", "size": 86.0, "rooms": 2, "bathrooms": 2, "address": "avenida Almirante Reis, 67", "province": "Lisboa", "municipality": "Arroios", "district": "Anjos", "country": "pt", "latitude": 38.7260325, "longitude": -9.1352167, "showAddress": true, "url": "https://www.idealista.pt/empreendimento/33386964/", "hasVideo": false, "status": "newdevelopment", "newDevelopment": true, "hasLift": true, "parkingSpace": {"hasParkingSpace": true, "isParkingSpaceIncludedInPrice": true}, "newDevelopmentFinished": false, "priceByArea": 7907.0, "detailedType": {"typology": "flat"}, "suggestedTexts": {"subtitle": "Arroios, Lisboa", "title": "Piso en avenida Almirante Reis, 67"}, "hasPlan": true, "has3DTour": false, "has360": false, "hasStaging": false, "topNewDevelopment": false, "topPlus": false}, {"propertyCode": "33386933", "thumbnail": "https://img3.idealista.pt/blur/WEB_LISTING/0/id.pro.pt.image.master/c7/08/81/243160963.jpg", "externalReference": "APA_9717", "numPhotos": 37, "floor": "2", "price": 2255000.0, "priceInfo": {"price": {"amount": 2255000.0}}, "propertyType": "flat", "operation": "sale", "size": 320.0, "rooms": 4, "bathrooms": 4, "address": "Largo do Rato - Estrela", "province": "Lisboa", "municipality": "Campo de Ourique", "district": "Largo do Rato - Estrela", "country": "pt", "latitude": 38.7160076, "longitude": -9.1535435, "showAddress": false, "url": "https://www.idealista.pt/imovel/33386933/", "hasVideo": true, "status": "good", "newDevelopment": false, "priceByArea": 7047.0, "detailedType": {"typology": "flat"}, "suggestedTexts": {"subtitle": "Campo de Ourique, Lisboa", "title": "Piso"}, "hasPlan": true, "has3DTour": false, "has360": false, "hasStaging": false, "highlight": {"groupDescription": "Destacado"}, "topNewDevelopment": false, "topPlus": false}, {"propertyCode": "33386861", "thumbnail": "https://img3.idealista.pt/blur/WEB_LISTING/0/id.pro.pt.image.master/ba/ed/05/243158436.jpg", "externalReference": "011230134", "numPhotos": 18, "price": 1002000.0, "priceInfo": {"price": {"amount": 1002000.0}}, "propertyType": "flat", "operation": "sale", "size": 142.0, "rooms": 3, "bathrooms": 3, "address": "Prazeres", "province": "Lisboa", "municipality": "Estrela", "district": "Prazeres", "country": "pt", "latitude": 38.7121833, "longitude": -9.1671981, "showAddress": false, "url": "https://www.idealista.pt/imovel/33386861/", "hasVideo": true, "status": "good", "newDevelopment": false, "hasLift": true, "parkingSpace": {"hasParkingSpace": true, "isParkingSpaceIncludedInPrice": true}, "priceByArea": 7056.0, "detailedType": {"typology": "flat"}, "suggestedTexts": {"subtitle": "Estrela, Lisboa", "title": "Piso"}, "hasPlan": true, "has3DTour": false, "has360": false, "hasStaging": false, "topNewDevelopment": false, "topPlus": false}, {"propertyCode": "33386856", "thumbnail": "https://img3.idealista.pt/blur/WEB_LISTING/0/id.pro.pt.image.master/f4/ac/59/243158435.jpg", "externalReference": "011230136", "numPhotos": 5, "price": 918000.0, "priceInfo": {"price": {"amount": 918000.0}}, "propertyType": "flat", "operation": "sale", "size": 130.0, "rooms": 3, "bathrooms": 3, "address": "Prazeres", "province": "Lisboa", "municipality": "Estrela", "district": "Prazeres", "country": "pt", "latitude": 38.7101239, "longitude": -9.1705985, "showAddress": false, "url": "https://www.idealista.pt/imovel/33386856/", "hasVideo": true, "status": "good", "newDevelopment": false, "hasLift": true, "parkingSpace": {"hasParkingSpace": true, "isParkingSpaceIncludedInPrice": true}, "priceByArea": 7062.0, "detailedType": {"typology": "flat"}, "suggestedTexts": {"subtitle": "Estrela, Lisboa", "title": "Piso"}, "hasPlan": true, "has3DTour": false, "has360": false, "hasStaging": false, "topNewDevelopment": false, "topPlus": false}, {"propertyCode": "33386849", "thumbnail": "https://img3.idealista.pt/blur/WEB_LISTING/0/id.pro.pt.image.master/7e/95/a3/243158407.jpg", "externalReference": "011230137", "numPhotos": 8, "price": 918000.0, "priceInfo": {"price": {"amount": 918000.0}}, "propertyType": "flat", "operation": "sale", "size": 130.0, "rooms": 2, "bathrooms": 2, "address": "Prazeres", "province": "Lisboa", "municipality": "Estrela", "district": "Prazeres", "country": "pt", "latitude": 38.7102765, "longitude": -9.1702245, "showAddress": false, "url": "https://www.idealista.pt/imovel/33386849/", "hasVideo": true, "status": "good", "newDevelopment": false, "hasLift": true, "parkingSpace": {"hasParkingSpace": true, "isParkingSpaceIncludedInPrice": true}, "priceByArea": 7062.0, "detailedType": {"typology": "flat"}, "suggestedTexts": {"subtitle": "Estrela, Lisboa", "title": "Piso"}, "hasPlan": true, "has3DTour": false, "has360": false, "hasStaging": false, "topNewDevelopment": false, "topPlus": false}, {"propertyCode": "32201537", "thumbnail": "https://img3.idealista.pt/blur/WEB_LISTING/0/id.pro.pt.image.master/31/74/9d/245255939.jpg", "externalReference": "PROP-026520", "numPhotos": 35, "price": 749000.0, "priceInfo": {"price": {"amount": 749000.0}}, "propertyType": "flat", "operation": "sale", "size": 133.0, "rooms": 2, "bathrooms": 2, "address": "Av. da Liberdade - Marqu\u00eas de Pombal", "province": "Lisboa", "municipality": "Santo Ant\u00f3nio", "district": "Av. da Liberdade - Marqu\u00eas de Pombal", "country": "pt", "latitude": 38.7197252, "longitude": -9.1510714, "showAddress": false, "url": "https://www.idealista.pt/imovel/32201537/", "hasVideo": true, "status": "good", "newDevelopment": false, "hasLift": false, "priceByArea": 5632.0, "detailedType": {"typology": "flat"}, "suggestedTexts": {"subtitle": "Santo Ant\u00f3nio, Lisboa", "title": "Piso"}, "hasPlan": true, "has3DTour": true, "has360": false, "hasStaging": false, "highlight": {"groupDescription": "Top"}, "topNewDevelopment": false, "topPlus": false}, {"propertyCode": "33386762", "thumbnail": "https://img3.idealista.pt/blur/WEB_LISTING/0/id.pro.pt.image.master/4f/33/30/243154753.jpg", "numPhotos": 42, "floor": "2", "price": 550000.0, "priceInfo": {"price": {"amount": 550000.0}}, "propertyType": "flat", "operation": "sale", "size": 85.0, "rooms": 1, "bathrooms": 1, "address": "Baixa", "province": "Lisboa", "municipality": "Santa Maria Maior", "district": "Baixa", "country": "pt", "latitude": 38.7124644, "longitude": -9.1370907, "showAddress": false, "url": "https://www.idealista.pt/imovel/33386762/", "description": "En el coraz\u00f3n de Baixa Chiado, este apartamento T1, adecuado tanto para residencia personal como para inversi\u00f3n, est\u00e1 listo para darle la bienvenida. Al entrar, quedar\u00e1 inmediatamente cautivado por sus caracter\u00edsticas pombalinas y su encanto tradicional. Los techos altos proporcionan una sensaci\u00f3n de amplitud y grandeza, mientras que los detalles arquitect\u00f3nicos conservados a\u00f1aden un toque de historia y autenticidad al ambiente. Ubicado en el segundo piso de un edificio hist\u00f3rico, este apartamento cuenta con 84 metros cuadrados de superficie bruta privada, ofreciendo espacio y comodidad para el d\u00eda a d\u00eda. La disposici\u00f3n inteligente garantiza una circulaci\u00f3n fluida y una atm\u00f3sfera acogedora en cada rinc\u00f3n de la casa. La sala de estar es el espacio perfecto para relajarse despu\u00e9s de un d\u00eda de trabajo o paseo por la ciudad. Con una decoraci\u00f3n cuidadosamente seleccionada que combina elementos tradicionales y contempor\u00e1neos, las persianas originales de madera restauradas permiten la entrada de luz natural y crean un ambiente acogedor durante todo el d\u00eda. La cocina est\u00e1 totalmente equipada con todos los utensilios y electrodom\u00e9sticos necesarios. Tambi\u00e9n cuenta con una sala separada con una puerta de hierro fundido de 3,2 metros de altura que alberga la lavadora y el calentador de agua. El \u00e1rea de comedor adyacente ofrece un espacio \u00edntimo para disfrutar de comidas en familia o con amigos. El dormitorio principal, decorado con buen gusto, ofrece un refugio para una noche de sue\u00f1o tranquilo. Aqu\u00ed sentir\u00e1s la energ\u00eda de la antigua Lisboa con la Cruz de San Andr\u00e9s en primer plano, armarios de cedro y vidrio. El ba\u00f1o, consistente con el resto del apartamento, cuenta con m\u00e1rmol rosa, una ducha a ras de suelo para mayor accesibilidad y una ventana al exterior. Adem\u00e1s, la ubicaci\u00f3n privilegiada de este apartamento te sit\u00faa a solo cinco minutos a pie del paseo mar\u00edtimo, donde podr\u00e1s disfrutar de impresionantes vistas del Tajo y explorar los pintorescos barrios hist\u00f3ricos de Lisboa. Con una variedad de restaurantes, tiendas, museos y atracciones culturales en las cercan\u00edas, este apartamento ofrece una base ideal para descubrir todo lo que esta ciudad tiene para ofrecer. Adem\u00e1s, la estaci\u00f3n de metro Baixa-Chiado est\u00e1 a 5 minutos a pie y el aeropuerto de Lisboa est\u00e1 a solo 20 minutos en coche. Nota: Actualmente, este apartamento se gestiona para alquileres de corta duraci\u00f3n, y el nuevo propietario puede continuar con este negocio. Para m\u00e1s informaci\u00f3n, por favor cont\u00e1ctenos.", "hasVideo": false, "status": "good", "newDevelopment": false, "hasLift": false, "priceByArea": 6471.0, "detailedType": {"typology": "flat"}, "suggestedTexts": {"subtitle": "Santa Maria Maior, Lisboa", "title": "Piso"}, "hasPlan": false, "has3DTour": false, "has360": false, "hasStaging": false, "topNewDevelopment": false, "topPlus": false}, {"propertyCode": "33385795", "thumbnail": "https://img3.idealista.pt/blur/WEB_LISTING/0/id.pro.pt.image.master/a7/1a/5a/243080642.jpg", "externalReference": "ILX-048/24", "numPhotos": 49, "floor": "2", "price": 540000.0, "priceInfo": {"price": {"amount": 540000.0}}, "propertyType": "flat", "operation": "sale", "size": 110.0, "rooms": 2, "bathrooms": 2, "address": "rua Principado de Andorra, 2", "province": "Lisboa", "municipality": "Benfica", "district": "Fonte Nova -  Calhariz", "country": "pt", "latitude": 38.7436869, "longitude": -9.2028424, "showAddress": true, "url": "https://www.idealista.pt/imovel/33385795/", "hasVideo": false, "status": "good", "newDevelopment": false, "hasLift": true, "parkingSpace": {"hasParkingSpace": true, "isParkingSpaceIncludedInPrice": true}, "priceByArea": 4909.0, "detailedType": {"typology": "flat"}, "suggestedTexts": {"subtitle": "Benfica, Lisboa", "title": "Piso en rua Principado de Andorra, 2"}, "hasPlan": true, "has3DTour": false, "has360": false, "hasStaging": false, "topNewDevelopment": false, "topPlus": false}, {"propertyCode": "33386586", "thumbnail": "https://img3.idealista.pt/blur/WEB_LISTING/0/id.pro.pt.image.master/47/d7/d8/243149531.jpg", "externalReference": "APTRR044", "numPhotos": 27, "floor": "2", "price": 399900.0, "priceInfo": {"price": {"amount": 399900.0}}, "propertyType": "flat", "operation": "sale", "size": 76.0, "rooms": 2, "bathrooms": 2, "address": "Estrada de Benfica", "province": "Lisboa", "municipality": "S\u00e3o Domingos de Benfica", "district": "Estrada de Benfica", "country": "pt", "latitude": 38.7477725, "longitude": -9.178501, "showAddress": false, "url": "https://www.idealista.pt/imovel/33386586/", "description": "Apartamento de 2 + 1 Dormitorios Recuperado y Amueblado en S\u00e3o Domingos de Benfica, que comprende: Cocina + Sala de estar con 45m2, la cocina tiene muebles blancos, azulejos en toda la pared detr\u00e1s de los muebles y est\u00e1 equipada con Horno, Placa de cocci\u00f3n, Campana extractora, Lavavajillas empotrado, Lavadora empotrada, Termoacumulador y Empotrado Combinado. Tambi\u00e9n cuenta con un ba\u00f1o completo de 3m2 y 2 dormitorios, el primero suite con 20m2 y armario y el segundo con 15m2 y armario. tambi\u00e9n cuenta con un ALTILLO con 35m2. Este Apartamento est\u00e1 equipado con marcos lacados en blanco con doble acristalamiento y topes de oscilaci\u00f3n, falso techo con luces led incorporadas, en toda la casa y Preinstalaci\u00f3n de Aire Acondicionado. Edificio TOTALMENTE RECUPERADO (Techo, agua, electricidad y columnas de alcantarillado, fachadas, escaleras, contadores, puerta del edificio. Ubicado en un barrio familiar y residencial con varios puntos de comercio y servicios. Comercio tradicional, tiendas de dise\u00f1o y muebles, caf\u00e9s y restaurantes Zona central, facilidad de acceso, proximidad al transporte p\u00fablico y a diversas instalaciones sociales, Mercado de S\u00e3o Domingos de Benfica, Alto dos Moinhos Metropolitan, Hospital de la Cruz Roja y Zool\u00f3gico.  Categor\u00eda Energ\u00e9tica: E  ref: APTRR044.", "hasVideo": false, "status": "good", "newDevelopment": false, "priceByArea": 5262.0, "detailedType": {"typology": "flat"}, "suggestedTexts": {"subtitle": "S\u00e3o Domingos de Benfica, Lisboa", "title": "Piso"}, "hasPlan": true, "has3DTour": false, "has360": false, "hasStaging": false, "topNewDevelopment": false, "topPlus": false}, {"propertyCode": "33386585", "thumbnail": "https://img3.idealista.pt/blur/WEB_LISTING/0/id.pro.pt.image.master/5f/c7/1a/243149433.jpg", "externalReference": "APTRR043", "numPhotos": 18, "price": 349900.0, "priceInfo": {"price": {"amount": 349900.0}}, "propertyType": "flat", "operation": "sale", "size": 67.0, "rooms": 2, "bathrooms": 2, "address": "Estrada de Benfica", "province": "Lisboa", "municipality": "S\u00e3o Domingos de Benfica", "district": "Estrada de Benfica", "country": "pt", "latitude": 38.7477867, "longitude": -9.1779879, "showAddress": false, "url": "https://www.idealista.pt/imovel/33386585/", "description": "Apartamento de 2 Dormitorios Recuperado y Amueblado en Benfica compuesto de la siguiente manera: Cocina m\u00e1s Sala de Estar con 35m2. La cocina tiene muebles blancos, azulejos por toda la pared detr\u00e1s de los muebles y est\u00e1 equipada con: Horno, vitrocer\u00e1mica, campana extractora, lavavajillas empotrado, lavadora empotrada, calentador de agua y frigor\u00edfico congelador empotrado. Tambi\u00e9n dispone de un ba\u00f1o completo de 3m2 y 2 dormitorios, el primero suite con 15m2 y armario y el segundo con 14m2 y armario. En este apartamento tambi\u00e9n se puede disfrutar de un PATIO con 11m2. Apartamento equipado con: Marcos lacados en blanco con doble acristalamiento y topes de oscilaci\u00f3n, Falso techo con luces LED incorporadas, en toda la vivienda y Preinstalaci\u00f3n de Aire Acondicionado. Edificio TOTALMENTE RECUPERADO (Techo, agua, electricidad y columnas de alcantarillado, fachadas, escaleras, contadores, puerta del edificio. Ubicado en un barrio familiar y residencial con varios puntos de comercio y servicios. Comercio tradicional, tiendas de dise\u00f1o y muebles, caf\u00e9s y restaurantes Zona central, facilidad de acceso, proximidad al transporte p\u00fablico y a diversas instalaciones sociales, Mercado de S\u00e3o Domingos de Benfica, Alto dos Moinhos Metropolitan, Hospital de la Cruz Roja y Zool\u00f3gico.  Categor\u00eda Energ\u00e9tica: D  ref: APTRR043.", "hasVideo": false, "status": "good", "newDevelopment": false, "priceByArea": 5222.0, "detailedType": {"typology": "flat"}, "suggestedTexts": {"subtitle": "S\u00e3o Domingos de Benfica, Lisboa", "title": "Piso"}, "hasPlan": true, "has3DTour": false, "has360": false, "hasStaging": false, "topNewDevelopment": false, "topPlus": false}, {"propertyCode": "33386273", "thumbnail": "https://img3.idealista.pt/blur/WEB_LISTING/0/id.pro.pt.image.master/7e/73/f3/243144099.jpg", "externalReference": "C0409-01215", "numPhotos": 33, "floor": "2", "price": 690000.0, "priceInfo": {"price": {"amount": 690000.0}}, "propertyType": "duplex", "operation": "sale", "size": 209.0, "rooms": 3, "bathrooms": 2, "address": "Santa Engr\u00e1cia", "province": "Lisboa", "municipality": "S\u00e3o Vicente", "district": "Santa Engr\u00e1cia", "country": "pt", "latitude": 38.7176687, "longitude": -9.1178912, "showAddress": false, "url": "https://www.idealista.pt/imovel/33386273/", "description": "Para personas apasionadas por el respirar de las ciudades, mirar con atenci\u00f3n el inmueble que ahora se presenta, es fundamental para agregar una elecci\u00f3n rom\u00e1ntica, inteligente y con una riqueza cultural embrionaria, como pocos emprendimientos poseen. Donde anta\u00f1o, a partir del siglo XVIII, se erigi\u00f3 la Iglesia de Nuestra Se\u00f1ora de la Porci\u00fancula y el Convento de los Barbadinhos Italianos, con el patrocinio del Rey D. Jo\u00e3o V, resistiendo a la erosi\u00f3n del tiempo y al terremoto de 1755, se llega a la actualidad con un conjunto habitacional impar, el Pa\u00e7o Convento dos Barbadinhos, con este T3 d\u00faplex que ahora puede ser suyo. Con una recuperaci\u00f3n de lo edificado, asentada en una elecci\u00f3n criteriosa de los acabados, como son ejemplo el list\u00f3n de madera pino de Riga en los pavimentos entarimados, el lajeado de Lioz pulido en el pavimento y paredes de la cocina y ba\u00f1os, las lindas contraventanas de madera maciza que abrazan todas las ventanas de PVC con vidrio doble, as\u00ed como las puertas y duelas interiores y armarios empotrados, tambi\u00e9n en madera maciza, confiriendo un encanto inigualable, colmado por las vigas de madera y escalera de acceso al segundo piso, para rematar el conjunto est\u00e9tico y estructural del inmueble. Equipado con calefacci\u00f3n central y aire acondicionado en todas las divisiones, cocina equipada con electrodom\u00e9sticos Miele, instalaciones sanitarias equipadas con loza Valadares, serie Nautilus y Douro y grifer\u00eda Groe, serie Allure, tanto en el WC Social como en la suite, son 160,00 m2 de \u00e1rea \u00fatil, con vista al r\u00edo, posible en todo el frente sur del primer piso, \u00a1como a partir de las buhardillas del segundo piso! Lisboa, de las mejores capitales europeas para vivir, en expansi\u00f3n por su margen norte del r\u00edo Tajo, en las cercan\u00edas de esta encantadora vivienda, convierte este T3 D\u00faplex en una inversi\u00f3n segura e inteligente. No lo dude, \u00a1venga a visitarnos! Nosotros le esperamos.", "hasVideo": false, "status": "good", "newDevelopment": false, "hasLift": true, "priceByArea": 3301.0, "detailedType": {"typology": "flat", "subTypology": "duplex"}, "suggestedTexts": {"subtitle": "S\u00e3o Vicente, Lisboa", "title": "D\u00faplex"}, "hasPlan": true, "has3DTour": false, "has360": false, "hasStaging": false, "topNewDevelopment": false, "topPlus": false}, {"propertyCode": "33386287", "thumbnail": "https://img3.idealista.pt/blur/WEB_LISTING/0/id.pro.pt.image.master/da/18/aa/243143975.jpg", "externalReference": "C0405-02724", "numPhotos": 50, "floor": "bj", "price": 430000.0, "priceInfo": {"price": {"amount": 430000.0}}, "propertyType": "flat", "operation": "sale", "size": 79.0, "rooms": 1, "bathrooms": 1, "address": "rua V\u00edtor Cordon", "province": "Lisboa", "municipality": "Santa Maria Maior", "district": "Chiado", "country": "pt", "latitude": 38.7060773, "longitude": -9.1391378, "showAddress": false, "url": "https://www.idealista.pt/imovel/33386287/", "description": "Explora el verdadero esp\u00edritu de Lisboa en este encantador apartamento en el coraz\u00f3n del Chiado. Este espacio t\u00edpicamente lisboeta, totalmente remodelado, conserva el encanto de los edificios tradicionales de la ciudad. Con un espacioso exterior para disfrutar del sol y la brisa de la capital, este inmueble es un verdadero oasis urbano. Con dos habitaciones, posee acabados caracter\u00edsticos, incluyendo el suelo de madera, que a\u00f1aden un toque de autenticidad y confort. Descubre el estilo de vida lisboeta en este encantador refugio. \u00a1Ahora estamos abiertos de lunes a domingo, ven a visitarnos! \u00a1Casas Son Pasiones!", "hasVideo": false, "status": "good", "newDevelopment": false, "hasLift": false, "priceByArea": 5443.0, "detailedType": {"typology": "flat"}, "suggestedTexts": {"subtitle": "Santa Maria Maior, Lisboa", "title": "Piso en rua V\u00edtor Cordon"}, "hasPlan": false, "has3DTour": false, "has360": false, "hasStaging": false, "topNewDevelopment": false, "topPlus": false}, {"propertyCode": "33386265", "thumbnail": "https://img3.idealista.pt/blur/WEB_LISTING/0/id.pro.pt.image.master/8a/7b/f4/243143612.jpg", "externalReference": "C0405-02727", "numPhotos": 20, "floor": "4", "price": 365000.0, "priceInfo": {"price": {"amount": 365000.0}}, "propertyType": "flat", "operation": "sale", "size": 68.0, "rooms": 2, "bathrooms": 1, "address": "rua Doutor Jos\u00e9 Baptista de Sousa", "province": "Lisboa", "municipality": "Benfica", "district": "Avenida do Uruguai", "country": "pt", "latitude": 38.7490309, "longitude": -9.1940142, "showAddress": false, "url": "https://www.idealista.pt/imovel/33386265/", "hasVideo": false, "status": "good", "newDevelopment": false, "hasLift": true, "priceByArea": 5368.0, "detailedType": {"typology": "flat"}, "suggestedTexts": {"subtitle": "Benfica, Lisboa", "title": "Piso en rua Doutor Jos\u00e9 Baptista de Sousa"}, "hasPlan": false, "has3DTour": false, "has360": false, "hasStaging": false, "topNewDevelopment": false, "topPlus": false}, {"propertyCode": "33386258", "thumbnail": "https://img3.idealista.pt/blur/WEB_LISTING/0/id.pro.pt.image.master/71/18/f9/243143368.jpg", "externalReference": "C0223-07067", "numPhotos": 23, "floor": "2", "price": 620000.0, "priceInfo": {"price": {"amount": 620000.0}}, "propertyType": "flat", "operation": "sale", "size": 80.0, "rooms": 2, "bathrooms": 2, "address": "Centro", "province": "Lisboa", "municipality": "Campolide", "district": "Centro", "country": "pt", "latitude": 38.7228603, "longitude": -9.1644181, "showAddress": false, "url": "https://www.idealista.pt/imovel/33386258/", "hasVideo": false, "status": "good", "newDevelopment": false, "hasLift": true, "parkingSpace": {"hasParkingSpace": true, "isParkingSpaceIncludedInPrice": true}, "priceByArea": 7750.0, "detailedType": {"typology": "flat"}, "suggestedTexts": {"subtitle": "Campolide, Lisboa", "title": "Piso"}, "hasPlan": true, "has3DTour": false, "has360": false, "hasStaging": false, "topNewDevelopment": false, "topPlus": false}, {"propertyCode": "33386236", "thumbnail": "https://img3.idealista.pt/blur/WEB_LISTING/0/id.pro.pt.image.master/a6/55/96/243142867.jpg", "externalReference": "C0514-00024", "numPhotos": 17, "floor": "3", "price": 190000.0, "priceInfo": {"price": {"amount": 190000.0}}, "propertyType": "flat", "operation": "sale", "size": 53.0, "rooms": 2, "bathrooms": 1, "address": "rua dos Corvos, 13", "province": "Lisboa", "municipality": "Santa Maria Maior", "district": "Alfama - S\u00e9", "country": "pt", "latitude": 38.7128806, "longitude": -9.1275863, "showAddress": true, "url": "https://www.idealista.pt/imovel/33386236/", "description": "Atenci\u00f3n Inversores. Apartamento en el que puede obtener una rentabilidad de aproximadamente el 6% en alojamiento de larga duraci\u00f3n. Este apartamento era un T1 de origen, habiendo sido transformado en un T2 en las \u00faltimas obras que recibi\u00f3 de mejora. El edificio que recientemente recibi\u00f3 obras de modernizaci\u00f3n, est\u00e1 compuesto por 3 fracciones, 1 apartamento por piso. El apartamento que tambi\u00e9n \u00e9l recibi\u00f3 obras de mejora, concretamente fontaner\u00eda y electricidad, est\u00e1 compuesto por: Hall de entrada que da acceso al agua hurtada, un peque\u00f1o balc\u00f3n con una linda y luminosa vista de r\u00edo con mucho sol donde se podr\u00e1 sentar, dos habitaciones, una de ellas con acceso a un trastero, una sala, un aseo y una cocina independiente, tambi\u00e9n ella con acceso a otro trastero. Apartamento est\u00e1 situado en plena Mouraria, en una calle peatonal. La Mouraria es un barrio multicultural donde puede encontrar bastante comercio local y restaurantes Asi\u00e1ticos, Portugueses, Africanos y \u00c1rabes. Queda pr\u00f3ximo del aclamado Pante\u00f3n Nacional y de la lind\u00edsima Iglesia de San Vicente de Fora. Las callejuelas empedradas e inclinadas est\u00e1n repletas de casas con varios siglos, donde se inserta la casa de la c\u00e9lebre fadista Mar\u00eda Severa Onofriana, en la Calle del Capell\u00e1n. Localizaci\u00f3n: Bomberos \u2013 600 metros Escuela B\u00e1sica Santa Clara \u2013 400 metros Escuela Secundaria Gil Vicente \u2013 750 metros Hospital de San Jos\u00e9 \u2013 1200 metros Escuela B2,3 Nuno Gon\u00e7alves \u2013 1700 metros Estaci\u00f3n de tren de Santa Apolonia \u2013 750 metros Metro de Santa Apolonia \u2013 750 metros Mercado de Santa Clara \u2013 450 metros Aeropuerto de Lisboa \u2013 8000 metros.", "hasVideo": false, "status": "good", "newDevelopment": false, "hasLift": false, "priceByArea": 3585.0, "detailedType": {"typology": "flat"}, "suggestedTexts": {"subtitle": "Santa Maria Maior, Lisboa", "title": "Piso en rua dos Corvos, 13"}, "hasPlan": true, "has3DTour": false, "has360": false, "hasStaging": false, "topNewDevelopment": false, "topPlus": false}, {"propertyCode": "33386158", "thumbnail": "https://img3.idealista.pt/blur/WEB_LISTING/0/id.pro.pt.image.master/ed/92/ac/243141441.jpg", "externalReference": "C0483-00681", "numPhotos": 32, "price": 425000.0, "priceInfo": {"price": {"amount": 425000.0}}, "propertyType": "flat", "operation": "sale", "size": 54.0, "rooms": 1, "bathrooms": 1, "address": "rua Doutor Est\u00eav\u00e3o de Vasconcelos, 4", "province": "Lisboa", "municipality": "Marvila", "country": "pt", "latitude": 38.7453986, "longitude": -9.1001152, "showAddress": true, "url": "https://www.idealista.pt/imovel/33386158/", "hasVideo": false, "status": "good", "newDevelopment": false, "hasLift": true, "priceByArea": 7870.0, "detailedType": {"typology": "flat"}, "suggestedTexts": {"subtitle": "Marvila, Lisboa", "title": "Piso en rua Doutor Est\u00eav\u00e3o de Vasconcelos, 4"}, "hasPlan": false, "has3DTour": false, "has360": false, "hasStaging": false, "topNewDevelopment": false, "topPlus": false}, {"propertyCode": "33386106", "thumbnail": "https://img3.idealista.pt/blur/WEB_LISTING/0/id.pro.pt.image.master/d7/e0/ef/243105504.jpg", "numPhotos": 40, "price": 2200000.0, "priceInfo": {"price": {"amount": 2200000.0}}, "propertyType": "chalet", "operation": "sale", "size": 364.0, "rooms": 5, "bathrooms": 6, "address": "estrada de Telheiras", "province": "Lisboa", "municipality": "Lumiar", "district": "Telheiras", "country": "pt", "latitude": 38.7582103, "longitude": -9.1625012, "showAddress": false, "url": "https://www.idealista.pt/imovel/33386106/", "description": "Vivienda en esquina de 5 dormitorios en 2 plantas con excelente exposici\u00f3n al sol en el casco hist\u00f3rico de Telheiras. Cerca de 364 m2 de superficie construida con un hermoso jard\u00edn (108,25m2) y un garaje para 2 veh\u00edculos y trasteros. 5 dormitorios, 3 suites, 6 aseos, cocina independiente pero en comunicaci\u00f3n directa con el comedor y la sala de estar. Perfecta divisi\u00f3n entre la zona social situada en la planta inferior y toda la zona privada (planta superior) Pasillos anchos y buen recibidor que potencian el volumen cuando estamos dentro de esta maravillosa vivienda. Posibilidad de poder a\u00f1adir valor al inmueble para obtener ingresos adicionales. Por ejemplo, mediante la conversi\u00f3n del garaje en apartamento independiente, ya que cuenta con luz natural, ba\u00f1o y acceso propio. Ubicaci\u00f3n excelente en calle privada y muy tranquila en la antigua Telheiras. Zona con excelentes accesos por carretera y bastante comercio local, a 3 minutos a pie de la estaci\u00f3n de metro de Telheiras y a 5 minutos en coche del Centro Comercial Colombo, del Continente de Telheiras, de la Escuela Alemana de Lisboa, del Colegio Militar, del Externato da Luz, del Colegio Mira Rio, del Colegio Manuel Bernardes del Colegio do Menino Jesus y del Colegio Planalto. A 10 minutos del Hospital da Luz, de la Universidad Europea y del Aeropuerto Humberto Delgado. \u00a1Venga a visitar su pr\u00f3xima residencia familiar!", "hasVideo": false, "status": "good", "newDevelopment": false, "parkingSpace": {"hasParkingSpace": true, "isParkingSpaceIncludedInPrice": true}, "priceByArea": 6044.0, "detailedType": {"typology": "chalet", "subTypology": "independantHouse"}, "suggestedTexts": {"subtitle": "Lumiar, Lisboa", "title": "Casa independiente en estrada de Telheiras"}, "hasPlan": false, "has3DTour": false, "has360": false, "hasStaging": false, "topNewDevelopment": false, "topPlus": false}, {"propertyCode": "33386103", "thumbnail": "https://img3.idealista.pt/blur/WEB_LISTING/0/id.pro.pt.image.master/8d/1c/0e/243271761.jpg", "externalReference": "C0483-00681", "numPhotos": 30, "floor": "3", "price": 425000.0, "priceInfo": {"price": {"amount": 425000.0}}, "propertyType": "flat", "operation": "sale", "size": 54.0, "rooms": 1, "bathrooms": 1, "address": "rua A ao Bra\u00e7o de Prata", "province": "Lisboa", "municipality": "Marvila", "country": "pt", "latitude": 38.7441084, "longitude": -9.1010664, "showAddress": false, "url": "https://www.idealista.pt/imovel/33386103/", "hasVideo": false, "status": "good", "newDevelopment": false, "hasLift": true, "parkingSpace": {"hasParkingSpace": true, "isParkingSpaceIncludedInPrice": true}, "priceByArea": 7870.0, "detailedType": {"typology": "flat"}, "suggestedTexts": {"subtitle": "Marvila, Lisboa", "title": "Piso en rua a ao Bra\u00e7o de Prata"}, "hasPlan": false, "has3DTour": false, "has360": false, "hasStaging": false, "topNewDevelopment": false, "topPlus": false}, {"propertyCode": "33386051", "thumbnail": "https://img3.idealista.pt/blur/WEB_LISTING/0/id.pro.pt.image.master/7d/79/6f/243950009.jpg", "externalReference": "TRI-102-24-AS", "numPhotos": 35, "floor": "1", "price": 318000.0, "priceInfo": {"price": {"amount": 318000.0}}, "propertyType": "flat", "operation": "sale", "size": 85.0, "rooms": 2, "bathrooms": 1, "address": "largo Conde Ottolini", "province": "Lisboa", "municipality": "S\u00e3o Domingos de Benfica", "district": "Estrada de Benfica", "country": "pt", "latitude": 38.745226, "longitude": -9.1777402, "showAddress": false, "url": "https://www.idealista.pt/imovel/33386051/", "description": "Apartamento de 2 dormitorios en S\u00e3o Domingos de Benfica. \u00bfEst\u00e1s buscando el lugar ideal para vivir con comodidad y calidad de vida en S\u00e3o Domingos de Benfica? \u00a1Este apartamento de 2 dormitorios es la elecci\u00f3n perfecta para ti! Ubicado en una de las zonas m\u00e1s tranquilas y valoradas de la ciudad, cerca de todo el comercio tradicional, el transporte p\u00fablico y los espacios verdes, este es el lugar ideal para vivir con todo el confort que te mereces. \u00a1No te pierdas esta oportunidad! Reserve ahora su visita y venga a conocer su nuevo hogar en S\u00e3o Domingos de Benfica. Financiamiento bancario: En Escadinhas da Cidade no solo te ayudamos a encontrar la casa ideal, sino que tambi\u00e9n facilitamos el proceso de financiaci\u00f3n a trav\u00e9s de una asociaci\u00f3n con servicios de intermediaci\u00f3n crediticia. Juntos, haremos que su proceso sea m\u00e1s simple y accesible. \u00a1Programe su visita ahora y descubra la casa de sus sue\u00f1os! Visite este y los dem\u00e1s establecimientos de.", "hasVideo": true, "status": "good", "newDevelopment": false, "hasLift": false, "priceByArea": 3741.0, "detailedType": {"typology": "flat"}, "suggestedTexts": {"subtitle": "S\u00e3o Domingos de Benfica, Lisboa", "title": "Piso en largo Conde Ottolini"}, "hasPlan": false, "has3DTour": false, "has360": true, "hasStaging": false, "topNewDevelopment": false, "topPlus": false}, {"propertyCode": "33385961", "thumbnail": "https://img3.idealista.pt/blur/WEB_LISTING/0/id.pro.pt.image.master/38/e2/36/243091741.jpg", "externalReference": "HT_50024", "numPhotos": 25, "floor": "3", "price": 580000.0, "priceInfo": {"price": {"amount": 580000.0}}, "propertyType": "flat", "operation": "sale", "size": 53.0, "rooms": 1, "bathrooms": 1, "address": "Pr\u00edncipe Real - S\u00e3o Bento", "province": "Lisboa", "municipality": "Miseric\u00f3rdia", "district": "Pr\u00edncipe Real - S\u00e3o Bento", "country": "pt", "latitude": 38.7157165, "longitude": -9.1484596, "showAddress": false, "url": "https://www.idealista.pt/imovel/33385961/", "description": "Piso de 53,20 m2 en venta en una de las tranquilas calles de Pr\u00edncipe Real en LIsboa Insertado en un edificio con pocos vecinos, que resulta de la rehabilitaci\u00f3n de un edificio del siglo XIX, donde la tradici\u00f3n, el encanto y los detalles del edificio fueron pensados con mucho cuidado para mantener.  Con ventanas y vistas sobre los tejados de Lisboa, el r\u00edo Tajo, las Amoreiras y la Iglesia. Con una excelente ubicaci\u00f3n en el cruce cada vez m\u00e1s cosmopolita de Palmeira, le permite caminar para disfrutar de uno de los mejores distritos comerciales de Lisboa, los palacios, teatros, as\u00ed como bares y restaurantes gourmet como se puede encontrar en Pr\u00edncipe Real! La rehabilitaci\u00f3n se realiz\u00f3 con el compromiso y la calidad de su bienestar y por lo tanto, se recuper\u00f3 manteniendo el encanto del pasado y garantizando el confort que la vida moderna exige. Quieres vivir en una ciudad con mucho encanto, y tener una experiencia maravillosa en Portugal, ven a vivir en este apartamento! \u00a1Ven a ver!", "hasVideo": true, "status": "good", "newDevelopment": false, "hasLift": true, "priceByArea": 10943.0, "detailedType": {"typology": "flat"}, "suggestedTexts": {"subtitle": "Miseric\u00f3rdia, Lisboa", "title": "Piso"}, "hasPlan": true, "has3DTour": false, "has360": false, "hasStaging": false, "topNewDevelopment": false, "topPlus": false}, {"propertyCode": "33385864", "thumbnail": "https://img3.idealista.pt/blur/WEB_LISTING/0/id.pro.pt.image.master/a3/69/37/243086931.jpg", "externalReference": "120611851-67", "numPhotos": 15, "floor": "2", "price": 220000.0, "priceInfo": {"price": {"amount": 220000.0}}, "propertyType": "flat", "operation": "sale", "size": 40.0, "rooms": 2, "bathrooms": 1, "address": "rua Madres, 5", "province": "Lisboa", "municipality": "Estrela", "district": "Santos-o-Velho - Madragoa", "country": "pt", "latitude": 38.7089767, "longitude": -9.1542812, "showAddress": true, "url": "https://www.idealista.pt/imovel/33385864/", "description": "Apartamento de 2 habitaciones en el centro de Lisboa con cocina americana con el sal\u00f3n. La cocina est\u00e1 equipada con cocina, campana extractora, microondas, lavadora y frigor\u00edfico. El ba\u00f1o completo tiene plato de ducha. Este confortable apartamento est\u00e1 situado en una zona con acceso a todo tipo de transportes y comercios. Se sit\u00faa en un segundo piso sin ascensor. Reserve ya su visita. *Dormitorios no registrados en la documentaci\u00f3n.", "hasVideo": false, "status": "good", "newDevelopment": false, "hasLift": false, "priceByArea": 5500.0, "detailedType": {"typology": "flat"}, "suggestedTexts": {"subtitle": "Estrela, Lisboa", "title": "Piso en rua Madres, 5"}, "hasPlan": false, "has3DTour": false, "has360": false, "hasStaging": false, "topNewDevelopment": false, "topPlus": false}, {"propertyCode": "32691779", "thumbnail": "https://img3.idealista.pt/blur/WEB_LISTING/0/id.pro.pt.image.master/71/88/96/230504015.jpg", "externalReference": "V0279LI", "numPhotos": 20, "floor": "bj", "price": 750000.0, "priceInfo": {"price": {"amount": 750000.0}}, "propertyType": "flat", "operation": "sale", "size": 97.0, "rooms": 1, "bathrooms": 1, "address": "rua das Janelas Verdes", "province": "Lisboa", "municipality": "Estrela", "district": "Lapa", "country": "pt", "latitude": 38.705069, "longitude": -9.1591193, "showAddress": false, "url": "https://www.idealista.pt/imovel/32691779/", "description": "1 dormitorio | Apartamento | 150 m2 | Condominio Cerrado | Gimnasio | Estrela Apartamento de 1 dormitorio, con 150 m2 de \u00e1rea bruta privada, 50m2 de terreno y 1 plaza de aparcamiento, insertado en un condominio con encanto, con piscina y gimnasio, situado en Janelas Verdes, en Lisboa. Totalmente equipado, con aire acondicionado y calefacci\u00f3n por suelo radiante, cocina equipada con electrodom\u00e9sticos BOSCH. Situado en Estrela, un barrio con mucho encanto en Lisboa, que conserva una identidad de exclusividad y se afirma como uno de los barrios m\u00e1s privilegiados de la ciudad. Esta zona de la Estrella, ofrece un r\u00e1pido acceso al barrio de Santos y \u00e0 zona ribeirinha, permaneciendo en la paz de una tiacute; pica calle de la Lapa. Tambi\u00e9n tiene un r\u00e1pido acceso al transporte p\u00fablico y el comercio local. Situado en Lapa, zona muy bien comunicada por el comercio y el transporte, cerca del Jardim da Estrela y Jardim y minutos de Santos.", "hasVideo": false, "status": "good", "newDevelopment": false, "hasLift": false, "priceByArea": 7732.0, "detailedType": {"typology": "flat"}, "suggestedTexts": {"subtitle": "Estrela, Lisboa", "title": "Piso en rua das Janelas Verdes"}, "hasPlan": true, "has3DTour": false, "has360": false, "hasStaging": false, "topNewDevelopment": false, "topPlus": false}, {"propertyCode": "33385752", "thumbnail": "https://img3.idealista.pt/blur/WEB_LISTING/0/id.pro.pt.image.master/e6/f1/cc/243072649.jpg", "externalReference": "ELL-5217", "numPhotos": 24, "floor": "4", "price": 650000.0, "priceInfo": {"price": {"amount": 650000.0}}, "propertyType": "flat", "operation": "sale", "size": 175.0, "rooms": 4, "bathrooms": 3, "address": "Bairro de Santa Cruz", "province": "Lisboa", "municipality": "Benfica", "district": "Bairro de Santa Cruz", "country": "pt", "latitude": 38.7463931, "longitude": -9.2075562, "showAddress": false, "url": "https://www.idealista.pt/imovel/33385752/", "hasVideo": false, "status": "good", "newDevelopment": false, "hasLift": true, "priceByArea": 3714.0, "detailedType": {"typology": "flat"}, "suggestedTexts": {"subtitle": "Benfica, Lisboa", "title": "Piso"}, "hasPlan": false, "has3DTour": false, "has360": false, "hasStaging": false, "topNewDevelopment": false, "topPlus": false}, {"propertyCode": "33385679", "thumbnail": "https://img3.idealista.pt/blur/WEB_LISTING/0/id.pro.pt.image.master/c1/e7/b3/243070580.jpg", "externalReference": "V0473LI", "numPhotos": 8, "floor": "3", "price": 925000.0, "priceInfo": {"price": {"amount": 925000.0}}, "propertyType": "flat", "operation": "sale", "size": 124.0, "rooms": 2, "bathrooms": 2, "address": "travessa do Fala-S\u00f3", "province": "Lisboa", "municipality": "Santo Ant\u00f3nio", "district": "Pra\u00e7a da Alegria", "country": "pt", "latitude": 38.7159648, "longitude": -9.1447392, "showAddress": false, "url": "https://www.idealista.pt/imovel/33385679/", "description": "Encantador Apartamento Nuevo de 2 dormitorios | 124.26 m2 | Balc\u00f3n | |Avenida Liberdade En el coraz\u00f3n de la ciudad, a pocos metros de la Avenida Liberdade este encantador apartamento de 2 dormitorios, completamente renovado, ofrece el privilegio de vivir en el coraz\u00f3n cosmopolita de la ciudad. El arquitecto, Samuel Torres de Carvalho, ha hecho una renovaci\u00f3n cuidadosa y con estilo a este edificio de 4 plantas, que garantiza la comodidad con elegancia y compromiso con la calidad. Algunas otras unidades todav\u00eda disponibles.", "hasVideo": false, "status": "good", "newDevelopment": false, "hasLift": false, "priceByArea": 7460.0, "detailedType": {"typology": "flat"}, "suggestedTexts": {"subtitle": "Santo Ant\u00f3nio, Lisboa", "title": "Piso en travessa do Fala-S\u00f3"}, "hasPlan": false, "has3DTour": false, "has360": false, "hasStaging": false, "topNewDevelopment": false, "topPlus": false}, {"propertyCode": "33385656", "thumbnail": "https://img3.idealista.pt/blur/WEB_LISTING/0/id.pro.pt.image.master/ac/e7/d7/243069452.jpg", "externalReference": "EB-EST", "numPhotos": 30, "floor": "4", "price": 600000.0, "priceInfo": {"price": {"amount": 600000.0}}, "propertyType": "flat", "operation": "sale", "size": 108.0, "rooms": 1, "bathrooms": 1, "address": "Cal\u00e7ada da Estrela, 207", "province": "Lisboa", "municipality": "Estrela", "district": "Lapa", "country": "pt", "latitude": 38.7130299, "longitude": -9.1586704, "showAddress": true, "url": "https://www.idealista.pt/imovel/33385656/", "hasVideo": true, "status": "good", "newDevelopment": false, "hasLift": false, "priceByArea": 5556.0, "detailedType": {"typology": "flat"}, "suggestedTexts": {"subtitle": "Estrela, Lisboa", "title": "Piso en Cal\u00e7ada da Estrela, 207"}, "hasPlan": true, "has3DTour": false, "has360": false, "hasStaging": false, "topNewDevelopment": false, "topPlus": false}, {"propertyCode": "32750689", "thumbnail": "https://img3.idealista.pt/blur/WEB_LISTING/0/id.pro.pt.image.master/37/4d/1f/218402721.jpg", "externalReference": "2964", "numPhotos": 23, "floor": "st", "price": 550000.0, "priceInfo": {"price": {"amount": 550000.0, "priceDropInfo": {"formerPrice": 565000.0, "priceDropValue": 15000, "priceDropPercentage": 3}}}, "propertyType": "flat", "operation": "sale", "size": 156.0, "rooms": 4, "bathrooms": 2, "address": "rua Gon\u00e7alves Crespo", "province": "Lisboa", "municipality": "Arroios", "district": "S\u00e3o Jorge de Arroios", "country": "pt", "neighborhood": "Estef\u00e2nia", "latitude": 38.7298245, "longitude": -9.1457691, "showAddress": false, "url": "https://www.idealista.pt/imovel/32750689/", "description": "Descubra este incre\u00edble apartamento, ubicado en una calle tranquila y privilegiada de Lisboa. Con una ubicaci\u00f3n envidiable, esta propiedad ofrece el equilibrio perfecto entre tranquilidad y comodidad. Caracteristicas de la propiedad: - 4 dormitorios para toda la familia; - Habitaci\u00f3n luminosa y acogedora, ideal para momentos de convivencia; - 2 ba\u00f1os modernos y bien equipados; - Cocina totalmente equipada con electrodom\u00e9sticos de alta calidad; - Mini Taza para comidas r\u00e1pidas y pr\u00e1cticas; - Amplia y encantadora terraza, equipada con barbacoa para momentos de ocio memorables; Acabados de Excelencia: - Materiales de alta calidad en todo el apartamento; - Detalles de buen gusto en cada acabado; - Techos renovados y pisos de madera nuevos en toda la casa; - Comodidad garantizada con aire acondicionado en casi todas las habitaciones; Ubicaci\u00f3n privilegiada: - Disfrute de la comodidad de poder caminar a lugares emblem\u00e1ticos como Saldanha, Avenida da Liberdade, Marqu\u00eas de Pombal y Parque Eduardo Vii. - La zona cuenta con una excelente red de transporte p\u00fablico, incluido el metro, lo que hace que el acceso a cualquier punto de la ciudad sea r\u00e1pido y sencillo. Servicios al alcance: Este apartamento est\u00e1 rodeado de una amplia gama de servicios, desde mercados de productos frescos, farmacias, restaurantes hasta excelentes colegios p\u00fablicos y privados. Viva en el coraz\u00f3n de la ciudad, a s\u00f3lo 700 metros de la ic\u00f3nica Avenida da Liberdade. Agenda tu visita ahora y enam\u00f3rate de este incre\u00edble apartamento.", "hasVideo": true, "status": "good", "newDevelopment": false, "hasLift": false, "priceByArea": 3526.0, "detailedType": {"typology": "flat"}, "suggestedTexts": {"subtitle": "Estef\u00e2nia, Lisboa", "title": "Piso en rua Gon\u00e7alves Crespo"}, "hasPlan": true, "has3DTour": false, "has360": false, "hasStaging": false, "highlight": {"groupDescription": "Top"}, "topNewDevelopment": false, "topPlus": false}, {"propertyCode": "33385527", "thumbnail": "https://img3.idealista.pt/blur/WEB_LISTING/0/id.pro.pt.image.master/72/28/59/243068513.jpg", "externalReference": "215240036", "numPhotos": 22, "floor": "6", "price": 435000.0, "priceInfo": {"price": {"amount": 435000.0}}, "propertyType": "flat", "operation": "sale", "size": 87.0, "rooms": 3, "bathrooms": 2, "address": "Fonte Nova -  Calhariz", "province": "Lisboa", "municipality": "Benfica", "district": "Fonte Nova -  Calhariz", "country": "pt", "latitude": 38.7462822, "longitude": -9.1921472, "showAddress": false, "url": "https://www.idealista.pt/imovel/33385527/", "hasVideo": false, "status": "good", "newDevelopment": false, "hasLift": true, "priceByArea": 5000.0, "detailedType": {"typology": "flat"}, "suggestedTexts": {"subtitle": "Benfica, Lisboa", "title": "Piso"}, "hasPlan": false, "has3DTour": false, "has360": false, "hasStaging": false, "topNewDevelopment": false, "topPlus": false}, {"propertyCode": "33385610", "thumbnail": "https://img3.idealista.pt/blur/WEB_LISTING/0/id.pro.pt.image.master/08/27/1e/243066949.jpg", "externalReference": "A-26914", "numPhotos": 12, "price": 219500.0, "priceInfo": {"price": {"amount": 219500.0}}, "propertyType": "flat", "operation": "sale", "size": 108.0, "rooms": 3, "bathrooms": 2, "address": "Marvila", "province": "Lisboa", "municipality": "Marvila", "country": "pt", "latitude": 38.7606681, "longitude": -9.1233349, "showAddress": false, "url": "https://www.idealista.pt/imovel/33385610/", "description": "PAULO MACHADO - 9_3_5_6_2_4_1_6_7 Apartamento T3 d\u00faplex en venta en Marvila de 108m2 con algunas mejoras que consta de: Sal\u00f3n de 30m2 con cocina americana, 3 habitaciones de 13,11 y 10m2 y 2 ba\u00f1os. Doble acristalamiento, Dos frentes solares. Luz natural en el 95% de la casa. Transportes en la puerta, comercios y cerca del Colegio Valsassina. Excelente como inversi\u00f3n para posterior alquiler. Este apartamento es perfecto para quien busca espacio, comodidad y excelente ubicaci\u00f3n. Su orientaci\u00f3n solar Naciente/Poniente garantiza luminosidad durante todo el d\u00eda. Insertado en un edificio de hormig\u00f3n armado en excelente estado. NOTA: INMUEBLE SITUADO EN LA PLANTA 6 CORRESPONDE A UN SEGUNDO PISO \u00a1Reserve ya su visita! Remax +Grupo Vantagem, existe para ayudarle a realizar sue\u00f1os, ya sea en la compra o venta de su inmueble \u00a1Nos encargamos de la aprobaci\u00f3n de su cr\u00e9dito! \u00a1No pierda m\u00e1s tiempo! \u00a1P\u00f3ngase en contacto con nosotros! Elegir el Grupo RE/MAX +VANTAGEM Significa: Optar por la red m\u00e1s eficiente de Asesores Inmobiliarios del Mercado, capaces de asesorarle y acompa\u00f1arle en la operaci\u00f3n de compra de su inmueble. Sea cual sea el valor de su inversi\u00f3n, siempre tendr\u00e1 la certeza de que su nuevo inmueble no es una parte de lo que hacemos, es todo lo que hacemos. (Llamada a la red m\u00f3vil Nacional).", "hasVideo": false, "status": "good", "newDevelopment": false, "priceByArea": 2032.0, "detailedType": {"typology": "flat"}, "suggestedTexts": {"subtitle": "Marvila, Lisboa", "title": "Piso"}, "hasPlan": false, "has3DTour": false, "has360": false, "hasStaging": false, "topNewDevelopment": false, "topPlus": false}, {"propertyCode": "33385605", "thumbnail": "https://img3.idealista.pt/blur/WEB_LISTING/0/id.pro.pt.image.master/51/3c/d6/243066667.jpg", "externalReference": "PR-230507", "numPhotos": 18, "floor": "2", "price": 399000.0, "priceInfo": {"price": {"amount": 399000.0}}, "propertyType": "flat", "operation": "sale", "size": 65.0, "rooms": 2, "bathrooms": 1, "address": "rua da Arr\u00e1bida", "province": "Lisboa", "municipality": "Campo de Ourique", "district": "Santa Isabel", "country": "pt", "latitude": 38.7211397, "longitude": -9.1618984, "showAddress": false, "url": "https://www.idealista.pt/imovel/33385605/", "description": "\u00a1Descubre tu nuevo hogar en la hist\u00f3rica Rua da Arr\u00e1bida de Lisboa! Este encantador apartamento de 87 m\u00b2 y 2 dormitorios ofrece la combinaci\u00f3n perfecta de tradici\u00f3n y potencial. Situada en un barrio emblem\u00e1tico, lleno de historia y cultura, esta propiedad es un lienzo en blanco a la espera de su visi\u00f3n creativa para la vivienda o la renovaci\u00f3n. Caracter\u00edsticas del apartamento:  Grandes Espacios: Ambientes de generosas proporciones con ventanas cl\u00e1sicas y suelos de parquet que evocan el encanto del pasado.  Abundante luz natural: Cada estancia est\u00e1 ba\u00f1ada de luz, gracias a los grandes ventanales que aseguran luminosidad durante todo el d\u00eda.  Flexibilidad: Un amplio pasillo de entrada conduce a dos dormitorios de gran tama\u00f1o y un ba\u00f1o, con el potencial de convertirse en dos.  Cocina espaciosa: Una cocina grande y luminosa, ideal para aquellos que aman cocinar y entretener a amigos y familiares. Ventajas de la ubicaci\u00f3n:  Transporte p\u00fablico: Accesibilidad simplificada con m\u00faltiples opciones de transporte p\u00fablico a poca distancia, lo que lo conecta f\u00e1cilmente con el resto de la ciudad.  Barrio vibrante: Vive en una zona que respira historia, rodeada de caf\u00e9s tradicionales, tiendas y lugares culturales. No pierdas la oportunidad de crear tu hogar en esta prestigiosa zona de Lisboa. \u00a1Programe una visita y venga a sentir el ambiente \u00fanico de la Rua da Arr\u00e1bida! \u00a1Cont\u00e1ctanos y agenda tu visita! Te esperamos para mostrarte tu futuro hogar. Compartimos este negocio con todas las agencias inmobiliarias. Si tiene un cliente comprador, \u00a1cont\u00e1ctenos!", "hasVideo": true, "status": "good", "newDevelopment": false, "hasLift": false, "priceByArea": 6138.0, "detailedType": {"typology": "flat"}, "suggestedTexts": {"subtitle": "Campo de Ourique, Lisboa", "title": "Piso en rua da Arr\u00e1bida"}, "hasPlan": true, "has3DTour": false, "has360": true, "hasStaging": false, "topNewDevelopment": false, "topPlus": false}, {"propertyCode": "33384738", "thumbnail": "https://img3.idealista.pt/blur/WEB_LISTING/0/id.pro.pt.image.master/7a/81/2f/243043876.jpg", "externalReference": "HT_40758", "numPhotos": 39, "price": 1420000.0, "priceInfo": {"price": {"amount": 1420000.0}}, "propertyType": "flat", "operation": "sale", "size": 200.0, "rooms": 3, "bathrooms": 3, "address": "Expo Central", "province": "Lisboa", "municipality": "Parque das Na\u00e7\u00f5es", "district": "Expo Central", "country": "pt", "latitude": 38.7693446, "longitude": -9.0946844, "showAddress": false, "url": "https://www.idealista.pt/imovel/33384738/", "description": "Apartamento D\u00faplex de 3 Dormitorios con Vista al R\u00edo, en Parque das Na\u00e7\u00f5es en una comunidad cerrada, con piscina, gimnasio, sala de reuniones y seguridad las 24 horas. Este apartamento con acabados de calidad superior, dise\u00f1o y un toque de modernidad consta de 2 plantas, 2 plazas de garaje, trastero e insertado en la 9\u00aa planta de la Torre de S\u00e3o Rafael. El apartamento de 123,5m2, balc\u00f3n con vistas al r\u00edo Tajo, tiene las siguientes divisiones: Amplio sal\u00f3n con 37m2, donde se puede crear f\u00e1cilmente una zona de estar y una zona de comedor, con un ventanal que ocupa todo el ancho con una vista \u00fanica y panor\u00e1mica sobre el r\u00edo Tajo y acceso a un balc\u00f3n con 20m2. Amplia cocina totalmente equipada con encimera de Silestone gris en armon\u00eda con los armarios termolaminados. Ba\u00f1o de visitas de dise\u00f1o. Suite con armario y aseo con lavabo suspendido con almacenaje y cabina de ducha. Dos dormitorios, ambos con armarios empotrados y vistas al r\u00edo. Ba\u00f1o de apoyo a la planta superior. El condominio garantiza un conserje con seguridad las 24 horas, piscina y gimnasio y sala de reuniones. Esta propiedad se encuentra en una zona de alta demanda en la ciudad de Lisboa, y es una inversi\u00f3n segura, ya sea para vivienda propia o para su posterior colocaci\u00f3n en el mercado de alquiler, ya que se encuentra al lado del transporte p\u00fablico, aeropuerto, todo tipo de comercio, servicios, hipermercado, escuelas y colegios (como el Colegio Internacional Ces\u00e1rio Verde o el Externato Jo\u00e3o XXIII), espacios verdes y culturales, cerca del Centro Comercial Vasco da Gama. ACABADOS: - Marcos met\u00e1licos con doble acristalamiento y caja de aire - Persianas el\u00e9ctricas -Climatizaci\u00f3n - Toalleros calefactables -Cofre -Videoportero - Puerta blindada de alta seguridad - 2 Plazas de aparcamiento privado - Almacenamiento individual A\u00f1o de construcci\u00f3n: 2005 Cuota de condominio: 190\u20ac/mes.", "hasVideo": false, "status": "good", "newDevelopment": false, "hasLift": true, "priceByArea": 7100.0, "detailedType": {"typology": "flat"}, "suggestedTexts": {"subtitle": "Parque das Na\u00e7\u00f5es, Lisboa", "title": "Piso"}, "hasPlan": true, "has3DTour": false, "has360": false, "hasStaging": false, "topNewDevelopment": false, "topPlus": false}, {"propertyCode": "33385363", "thumbnail": "https://img3.idealista.pt/blur/WEB_LISTING/0/id.pro.pt.image.master/d0/8b/06/243059556.jpg", "externalReference": "CD.11260.03.(A)", "numPhotos": 46, "floor": "1", "price": 399900.0, "priceInfo": {"price": {"amount": 399900.0}}, "propertyType": "flat", "operation": "sale", "size": 44.0, "rooms": 1, "bathrooms": 2, "address": "Laranjeiras", "province": "Lisboa", "municipality": "S\u00e3o Domingos de Benfica", "district": "Laranjeiras", "country": "pt", "latitude": 38.7514321, "longitude": -9.1699346, "showAddress": false, "url": "https://www.idealista.pt/imovel/33385363/", "hasVideo": false, "status": "good", "newDevelopment": false, "hasLift": false, "priceByArea": 9089.0, "detailedType": {"typology": "flat"}, "suggestedTexts": {"subtitle": "S\u00e3o Domingos de Benfica, Lisboa", "title": "Piso"}, "hasPlan": false, "has3DTour": false, "has360": false, "hasStaging": false, "topNewDevelopment": false, "topPlus": false}, {"propertyCode": "33385382", "thumbnail": "https://img3.idealista.pt/blur/WEB_LISTING/0/id.pro.pt.image.master/2f/76/b6/243059017.jpg", "externalReference": "121021478-10", "numPhotos": 21, "price": 475000.0, "priceInfo": {"price": {"amount": 475000.0}}, "propertyType": "flat", "operation": "sale", "size": 72.0, "rooms": 1, "bathrooms": 1, "address": "Lapa", "province": "Lisboa", "municipality": "Estrela", "district": "Lapa", "country": "pt", "latitude": 38.7067941, "longitude": -9.1677448, "showAddress": false, "url": "https://www.idealista.pt/imovel/33385382/", "hasVideo": false, "status": "good", "newDevelopment": false, "priceByArea": 6597.0, "detailedType": {"typology": "flat"}, "suggestedTexts": {"subtitle": "Estrela, Lisboa", "title": "Piso"}, "hasPlan": true, "has3DTour": false, "has360": false, "hasStaging": false, "topNewDevelopment": false, "topPlus": false}, {"propertyCode": "33385214", "thumbnail": "https://img3.idealista.pt/blur/WEB_LISTING/0/id.pro.pt.image.master/d2/67/8a/243058381.jpg", "externalReference": "334240028", "numPhotos": 16, "floor": "2", "price": 520000.0, "priceInfo": {"price": {"amount": 520000.0}}, "propertyType": "flat", "operation": "sale", "size": 58.0, "rooms": 1, "bathrooms": 1, "address": "largo da Gra\u00e7a", "province": "Lisboa", "municipality": "S\u00e3o Vicente", "district": "Gra\u00e7a", "country": "pt", "latitude": 38.7165549, "longitude": -9.1289994, "showAddress": false, "url": "https://www.idealista.pt/imovel/33385214/", "hasVideo": false, "status": "good", "newDevelopment": false, "hasLift": true, "parkingSpace": {"hasParkingSpace": true, "isParkingSpaceIncludedInPrice": true}, "priceByArea": 8966.0, "detailedType": {"typology": "flat"}, "suggestedTexts": {"subtitle": "S\u00e3o Vicente, Lisboa", "title": "Piso en largo da Gra\u00e7a"}, "hasPlan": true, "has3DTour": false, "has360": false, "hasStaging": false, "topNewDevelopment": false, "topPlus": false}, {"propertyCode": "33385350", "thumbnail": "https://img3.idealista.pt/blur/WEB_LISTING/0/id.pro.pt.image.master/62/e8/8a/243058453.jpg", "externalReference": "122911385-87", "numPhotos": 20, "price": 570000.0, "priceInfo": {"price": {"amount": 570000.0}}, "propertyType": "flat", "operation": "sale", "size": 126.0, "rooms": 3, "bathrooms": 2, "address": "Largo do Calv\u00e1rio - Lx Factory", "province": "Lisboa", "municipality": "Alc\u00e2ntara", "district": "Largo do Calv\u00e1rio - Lx Factory", "country": "pt", "latitude": 38.7073009, "longitude": -9.1772577, "showAddress": false, "url": "https://www.idealista.pt/imovel/33385350/", "description": "Bienvenido a su refugio soleado en Alc\u00e1ntara, donde el lujo y la comodidad se encuentran en este deslumbrante d\u00faplex de 3 dormitorios. Ubicado en una posici\u00f3n privilegiada, este inmueble es una invitaci\u00f3n irresistible a una vida llena de luminosidad y elegancia. Al entrar en este d\u00faplex, es imposible no encantarse con la abundancia de luz natural que inunda cada rinc\u00f3n, gracias a las amplias ventanas equipadas con doble acristalamiento. Su orientaci\u00f3n sur garantiza que los rayos dorados del sol iluminen cada espacio, creando una atm\u00f3sfera c\u00e1lida y acogedora a lo largo del d\u00eda, mientras que las vistas panor\u00e1micas proporcionan un espect\u00e1culo visual \u00fanico en cada momento. Con 3 espaciosas habitaciones y dos modernos ba\u00f1os completamente remodelados, este apartamento de 3 dormitorios ofrece el equilibrio perfecto entre estilo contempor\u00e1neo y funcionalidad pr\u00e1ctica. Cada detalle ha sido cuidadosamente considerado, desde los elegantes acabados hasta los materiales, incluyendo la carpinter\u00eda de PVC, proporcionando no solo aislamiento t\u00e9rmico, sino tambi\u00e9n una est\u00e9tica moderna y duradera. La comodidad no se detiene ah\u00ed. Este d\u00faplex est\u00e1 equipado con sistema de aire acondicionado, garantizando un ambiente agradable en todas las estaciones del a\u00f1o. Ya sea disfrutando del sol radiante que entra por las ventanas de doble acristalamiento o relaj\u00e1ndose a una temperatura ideal, esta casa es un santuario de bienestar. La cocina, tambi\u00e9n renovada y equipada, es una invitaci\u00f3n a la cocina creativa, mientras que la sala de estar, con unos 50m2, se destaca como el lugar perfecto para reunir amigos y familiares. La atm\u00f3sfera es luminosa y aireada. Este d\u00faplex de 3 dormitorios en Alc\u00e1ntara es m\u00e1s que una casa; es un estilo de vida. Venga a descubrir la armon\u00eda entre el dise\u00f1o moderno, la comodidad y la energ\u00eda vibrante de este barrio \u00fanico. Una oportunidad \u00fanica de residir en un lugar donde cada detalle refleja el cuidado y la dedicaci\u00f3n en brindar una experiencia de vida excepcional.", "hasVideo": false, "status": "good", "newDevelopment": false, "priceByArea": 4524.0, "detailedType": {"typology": "flat"}, "suggestedTexts": {"subtitle": "Alc\u00e2ntara, Lisboa", "title": "Piso"}, "hasPlan": false, "has3DTour": false, "has360": false, "hasStaging": false, "topNewDevelopment": false, "topPlus": false}, {"propertyCode": "33385316", "thumbnail": "https://img3.idealista.pt/blur/WEB_LISTING/0/id.pro.pt.image.master/15/a8/b2/243058586.jpg", "externalReference": "V0472LI", "numPhotos": 7, "floor": "2", "price": 750000.0, "priceInfo": {"price": {"amount": 750000.0}}, "propertyType": "flat", "operation": "sale", "size": 113.0, "rooms": 2, "bathrooms": 2, "address": "travessa do Fala-S\u00f3", "province": "Lisboa", "municipality": "Santo Ant\u00f3nio", "district": "Pra\u00e7a da Alegria", "country": "pt", "latitude": 38.7170751, "longitude": -9.1454343, "showAddress": false, "url": "https://www.idealista.pt/imovel/33385316/", "hasVideo": false, "status": "good", "newDevelopment": false, "hasLift": false, "priceByArea": 6637.0, "detailedType": {"typology": "flat"}, "suggestedTexts": {"subtitle": "Santo Ant\u00f3nio, Lisboa", "title": "Piso en travessa do Fala-S\u00f3"}, "hasPlan": false, "has3DTour": false, "has360": false, "hasStaging": false, "topNewDevelopment": false, "topPlus": false}, {"propertyCode": "33385218", "thumbnail": "https://img3.idealista.pt/blur/WEB_LISTING/0/id.pro.pt.image.master/45/54/dd/243058429.jpg", "externalReference": "V0454LI", "numPhotos": 6, "floor": "bj", "price": 595000.0, "priceInfo": {"price": {"amount": 595000.0}}, "propertyType": "flat", "operation": "sale", "size": 103.0, "rooms": 1, "bathrooms": 1, "address": "travessa do Fala-S\u00f3", "province": "Lisboa", "municipality": "Santo Ant\u00f3nio", "district": "Pra\u00e7a da Alegria", "country": "pt", "latitude": 38.7141417, "longitude": -9.1446207, "showAddress": false, "url": "https://www.idealista.pt/imovel/33385218/", "description": "Piso 1 dormitorio | nuevo | 103,72 m2 | balc\u00f3n | centro de Lisboa | Avenida Liberdade En el coraz\u00f3n de la ciudad, a pocos metros de la Avenida Liberdade, este piso d\u00faplex completamente renovado ofrece el privilegio de vivir en el centro cosmopolita y vibrante de Lisboa. El arquitecto, Samuel Torres de Carvalho, ha llevado a cabo una cuidada y elegante reforma que garantiza confort con elegancia y compromiso de calidad. En la planta baja se encuentra la sala de estar y una cocina moderna y totalmente equipada, as\u00ed como un aseo. En la 1\u00aa planta encontrar\u00e1 un dormitorio en suite.", "hasVideo": false, "status": "good", "newDevelopment": false, "hasLift": false, "priceByArea": 5777.0, "detailedType": {"typology": "flat"}, "suggestedTexts": {"subtitle": "Santo Ant\u00f3nio, Lisboa", "title": "Piso en travessa do Fala-S\u00f3"}, "hasPlan": false, "has3DTour": false, "has360": false, "hasStaging": false, "topNewDevelopment": false, "topPlus": false}, {"propertyCode": "33385240", "thumbnail": "https://img3.idealista.pt/blur/WEB_LISTING/0/id.pro.pt.image.master/3b/75/cf/243056074.jpg", "externalReference": "126911003-14", "numPhotos": 35, "price": 427000.0, "priceInfo": {"price": {"amount": 427000.0}}, "propertyType": "flat", "operation": "sale", "size": 116.0, "rooms": 3, "bathrooms": 2, "address": "avenida Almirante Reis s/n", "province": "Lisboa", "municipality": "Arroios", "district": "S\u00e3o Jorge de Arroios", "country": "pt", "neighborhood": "Alameda - Pra\u00e7a do Chile - Almirante Reis", "latitude": 38.7358704, "longitude": -9.1340202, "showAddress": true, "url": "https://www.idealista.pt/imovel/33385240/", "description": "Apartamento de 3 dormitorios y 1 ba\u00f1o, situado en una ubicaci\u00f3n privilegiada en Almirante Reis, entre la Plaza de Areeiro y la Alameda D. Afonso Henriques, a 500 metros del Instituto Superior T\u00e9cnico. Oportunidad \u00fanica de adquirir un apartamento para inversi\u00f3n (excelente para alquilar a estudiantes) o incluso para vivienda propia. Este apartamento, situado en un 4\u00ba piso, est\u00e1 orientado al este/oeste, donde podr\u00e1 disfrutar de una luminosidad y exposici\u00f3n solar excepcionales. Edificio compuesto de planta baja m\u00e1s 4 plantas con 2 fuegos/piso, con escaleras anchas y sin ascensor. Descubra la elegancia en este apartamento de 116m2 que dispone de una distribuci\u00f3n funcional donde incluye un pasillo, tres amplios dormitorios (uno de ellos con balc\u00f3n), un sal\u00f3n y comedor, una cocina totalmente equipada, un c\u00f3modo trastero al lado de la cocina, dos ba\u00f1os y un balc\u00f3n cerrado (marquesina). Este apartamento ha sido objeto de algunas renovaciones, con cocina y ba\u00f1os actualizados y carpinter\u00eda de aluminio lacado con doble acristalamiento, conservando su encanto original, como los techos altos, los techos estucados y trabajados, las contraventanas de madera, el suelo de tablones y los z\u00f3calos altos. Ubicaci\u00f3n: Inmensa variedad de comercios y servicios en los alrededores, como supermercados, tiendas de comestibles, carnicer\u00edas, cafeter\u00edas, restaurantes, papeler\u00edas, bancos, farmacias, lavander\u00edas, gasolineras, entre otros; IST a 500m (7 min a pie); Excelentes accesos por carretera con la Av. Almirante Gago Coutinho y la Av. Marechal Ant\u00f3nio Sp\u00ednola a pocos metros. Muy bien comunicado por transporte p\u00fablico, con autob\u00fas en la puerta y metro de Alameda (l\u00ednea roja y l\u00ednea verde) a 2 minutos a pie. El 4\u00ba piso derecha y la planta baja derecha del mismo edificio se pueden vender junto con este apartamento. \u00a1Reserve ya su visita!", "hasVideo": false, "status": "good", "newDevelopment": false, "priceByArea": 3681.0, "detailedType": {"typology": "flat"}, "suggestedTexts": {"subtitle": "Alameda - Pra\u00e7a do Chile - Almirante Reis, Lisboa", "title": "Piso en avenida Almirante Reis s/n"}, "hasPlan": true, "has3DTour": false, "has360": false, "hasStaging": false, "topNewDevelopment": false, "topPlus": false}, {"propertyCode": "33385238", "thumbnail": "https://img3.idealista.pt/blur/WEB_LISTING/0/id.pro.pt.image.master/72/07/fc/243056016.jpg", "externalReference": "126911003-12", "numPhotos": 33, "price": 547000.0, "priceInfo": {"price": {"amount": 547000.0}}, "propertyType": "flat", "operation": "sale", "size": 140.0, "rooms": 2, "bathrooms": 2, "address": "avenida Almirante Reis s/n", "province": "Lisboa", "municipality": "Arroios", "district": "S\u00e3o Jorge de Arroios", "country": "pt", "neighborhood": "Alameda - Pra\u00e7a do Chile - Almirante Reis", "latitude": 38.7358704, "longitude": -9.1340202, "showAddress": true, "url": "https://www.idealista.pt/imovel/33385238/", "hasVideo": false, "status": "good", "newDevelopment": false, "priceByArea": 3907.0, "detailedType": {"typology": "flat"}, "suggestedTexts": {"subtitle": "Alameda - Pra\u00e7a do Chile - Almirante Reis, Lisboa", "title": "Piso en avenida Almirante Reis s/n"}, "hasPlan": false, "has3DTour": false, "has360": false, "hasStaging": false, "topNewDevelopment": false, "topPlus": false}, {"propertyCode": "33385226", "thumbnail": "https://img3.idealista.pt/blur/WEB_LISTING/0/id.pro.pt.image.master/54/36/62/243055909.jpg", "externalReference": "120881430-9", "numPhotos": 45, "price": 180000.0, "priceInfo": {"price": {"amount": 180000.0}}, "propertyType": "flat", "operation": "sale", "size": 48.0, "rooms": 1, "bathrooms": 1, "address": "rua Actor Augusto de Melo s/n", "province": "Lisboa", "municipality": "Beato", "country": "pt", "latitude": 38.7350426, "longitude": -9.1135323, "showAddress": true, "url": "https://www.idealista.pt/imovel/33385226/", "description": "Apartamento de 1 dormitorio en venta Este apartamento le ofrece la oportunidad de adquirir una propiedad en el centro de la capital y vivir en una zona acogedora y prestigiosa. Un apartamento ideal para solteros o parejas j\u00f3venes que buscan un espacio c\u00f3modo, compuesto por una habitaci\u00f3n, una sala, cocina cerrada, un ba\u00f1o con ducha y hall de entrada. Se encuentra en una zona con todo tipo de servicios y comercios, muy cerca de transportes y de la estaci\u00f3n de metro de Olaias. Venga a conocer este magn\u00edfico apartamento. \u00a1Reserve ya su visita!", "hasVideo": true, "status": "good", "newDevelopment": false, "hasLift": false, "priceByArea": 3750.0, "detailedType": {"typology": "flat"}, "suggestedTexts": {"subtitle": "Beato, Lisboa", "title": "Piso en rua Actor Augusto de Melo s/n"}, "hasPlan": true, "has3DTour": false, "has360": false, "hasStaging": false, "topNewDevelopment": false, "topPlus": false}, {"propertyCode": "33385210", "thumbnail": "https://img3.idealista.pt/blur/WEB_LISTING/0/id.pro.pt.image.master/8d/40/f6/243055475.jpg", "externalReference": "334240027", "numPhotos": 16, "floor": "1", "price": 550000.0, "priceInfo": {"price": {"amount": 550000.0}}, "propertyType": "flat", "operation": "sale", "size": 73.0, "rooms": 1, "bathrooms": 1, "address": "largo da Gra\u00e7a", "province": "Lisboa", "municipality": "S\u00e3o Vicente", "district": "Gra\u00e7a", "country": "pt", "latitude": 38.7153784, "longitude": -9.1313141, "showAddress": false, "url": "https://www.idealista.pt/imovel/33385210/", "description": "Jard\u00edn de la Gloria | T1 insertado en Condominio Privado 73m2 \u00c1rea Bruta Privada 10m2 Terraza 1 Plaza de aparcamiento Explore el encanto contempor\u00e1neo de este elegante apartamento T1, que ofrece el equilibrio perfecto entre confort y sofisticaci\u00f3n. Disfrute de momentos relajantes en la terraza de 10m\u00b2, perfecta para entretenerse o simplemente disfrutar del aire fresco. Los 29m\u00b2 de la espaciosa sala/cocina proporcionan un ambiente acogedor para convivir y preparar sus comidas favoritas. El dormitorio de 11m\u00b2 ofrece un refugio tranquilo para descansar, mientras que el moderno cuarto de ba\u00f1o de 4m\u00b2 y el \u00e1rea de lavander\u00eda de 7m\u00b2 a\u00f1aden practicidad a su d\u00eda a d\u00eda. \u00a1Reserve una visita hoy y d\u00e9 el siguiente paso hacia la vida de sus sue\u00f1os!", "hasVideo": false, "status": "good", "newDevelopment": false, "hasLift": true, "parkingSpace": {"hasParkingSpace": true, "isParkingSpaceIncludedInPrice": true}, "priceByArea": 7534.0, "detailedType": {"typology": "flat"}, "suggestedTexts": {"subtitle": "S\u00e3o Vicente, Lisboa", "title": "Piso en largo da Gra\u00e7a"}, "hasPlan": true, "has3DTour": false, "has360": false, "hasStaging": false, "topNewDevelopment": false, "topPlus": false}, {"propertyCode": "33385208", "thumbnail": "https://img3.idealista.pt/blur/WEB_LISTING/0/id.pro.pt.image.master/49/32/90/243055368.jpg", "externalReference": "122081421-39", "numPhotos": 15, "price": 550000.0, "priceInfo": {"price": {"amount": 550000.0}}, "propertyType": "flat", "operation": "sale", "size": 149.0, "rooms": 3, "bathrooms": 2, "address": "Anjos", "province": "Lisboa", "municipality": "Arroios", "district": "Anjos", "country": "pt", "latitude": 38.7209985, "longitude": -9.1346647, "showAddress": false, "url": "https://www.idealista.pt/imovel/33385208/", "description": "Fant\u00e1stico Apartamento de 3 dormitorios en venta en Lisboa en un edificio de 2003, con ascensor en Anjos. \u00a1Bienvenido a su futura residencia! Presentamos este espectacular Apartamento en venta, una verdadera joya situada en la zona de Anjos, en Lisboa. Ubicado en el 1er piso del edificio \"Leao\", una de las referencias arquitect\u00f3nicas de la zona de Anjos en Lisboa. El edificio fue completamente rehabilitado en 2003, habiendo sufrido entre otras las mejoras la introducci\u00f3n de un ascensor, actualizaci\u00f3n integral de la red de agua, alcantarillado, electricidad y telecomunicaciones. Trat\u00e1ndose de un edificio de referencia en Anjos, esta propiedad ofrece el equilibrio perfecto entre confort, elegancia y proximidad a todo tipo de comercio, servicios y transportes para f\u00e1cil acceso y desplazamiento en Lisboa, lo que lo hace perfecto para familias que buscan un apartamento contempor\u00e1neo para llamar \"hogar\", con un encanto y car\u00e1cter \u00fanico. Caracter\u00edsticas de la propiedad: Tipo de Propiedad: Apartamento de 3 dormitorios en el 1er piso (edificio de 6 pisos) Ubicaci\u00f3n: Rua Andrade, 63, Anjos en Lisboa A\u00f1o de Construcci\u00f3n: 2003 \u00c1rea Bruta Privada: 148,9 m2 \u00c1rea Bruta \u00datil: 111,34 m2 Habitaciones: 3 (1 Habitaci\u00f3n suite) Ba\u00f1os: 2 Balcones / Terraza: S\u00ed (3 Balcones, 1 con vista despejada) Garaje / Estacionamiento: No Trastero: No Ascensor: S\u00ed Vista: Ciudad Estado: Como nuevo Acabados del Apartamento: Carpinter\u00eda: Carpinter\u00eda de aluminio con doble acristalamiento Puerta de entrada: Puerta Blindada Pavimentos: Pavimento de madera maciza Armarios empotrados: No incluidos Cocina: Semi-equipada (Placa, Horno y Campana extractora) Calefacci\u00f3n de Agua: Calentador o caldera (no incluido) 5 Razones para elegir este apartamento en venta en Lisboa: Dise\u00f1o Cl\u00e1sico, pero Funcional.", "hasVideo": false, "status": "good", "newDevelopment": false, "priceByArea": 3691.0, "detailedType": {"typology": "flat"}, "suggestedTexts": {"subtitle": "Arroios, Lisboa", "title": "Piso"}, "hasPlan": false, "has3DTour": false, "has360": false, "hasStaging": false, "topNewDevelopment": false, "topPlus": false}, {"propertyCode": "33385162", "thumbnail": "https://img3.idealista.pt/blur/WEB_LISTING/0/id.pro.pt.image.master/72/33/50/243057147.jpg", "externalReference": "APA_EUA", "numPhotos": 52, "floor": "10", "price": 678000.0, "priceInfo": {"price": {"amount": 678000.0}}, "propertyType": "flat", "operation": "sale", "size": 150.0, "rooms": 4, "bathrooms": 3, "address": "avenida dos Estados Unidos da Am\u00e9rica", "province": "Lisboa", "municipality": "Alvalade", "district": "Alvalade", "country": "pt", "latitude": 38.7502766, "longitude": -9.136943, "showAddress": false, "url": "https://www.idealista.pt/imovel/33385162/", "hasVideo": false, "status": "renew", "newDevelopment": false, "hasLift": true, "priceByArea": 4520.0, "detailedType": {"typology": "flat"}, "suggestedTexts": {"subtitle": "Alvalade, Lisboa", "title": "Piso en avenida dos Estados Unidos da Am\u00e9rica"}, "hasPlan": true, "has3DTour": false, "has360": true, "hasStaging": false, "topNewDevelopment": false, "topPlus": false}, {"propertyCode": "33384945", "thumbnail": "https://img3.idealista.pt/blur/WEB_LISTING/0/id.pro.pt.image.master/41/c3/df/243052748.jpg", "externalReference": "334240029", "numPhotos": 16, "floor": "3", "price": 895000.0, "priceInfo": {"price": {"amount": 895000.0}}, "propertyType": "penthouse", "operation": "sale", "size": 137.0, "rooms": 2, "bathrooms": 3, "address": "largo da Gra\u00e7a", "province": "Lisboa", "municipality": "S\u00e3o Vicente", "district": "Gra\u00e7a", "country": "pt", "latitude": 38.7158824, "longitude": -9.1282476, "showAddress": false, "url": "https://www.idealista.pt/imovel/33384945/", "hasVideo": false, "status": "good", "newDevelopment": false, "hasLift": true, "parkingSpace": {"hasParkingSpace": true, "isParkingSpaceIncludedInPrice": true}, "priceByArea": 6533.0, "detailedType": {"typology": "flat", "subTypology": "penthouse"}, "suggestedTexts": {"subtitle": "S\u00e3o Vicente, Lisboa", "title": "\u00c1tico en largo da Gra\u00e7a"}, "hasPlan": true, "has3DTour": false, "has360": false, "hasStaging": false, "topNewDevelopment": false, "topPlus": false}, {"propertyCode": "33385144", "thumbnail": "https://img3.idealista.pt/blur/WEB_LISTING/0/id.pro.pt.image.master/a6/1a/09/243053271.jpg", "externalReference": "125771033-4", "numPhotos": 24, "price": 285000.0, "priceInfo": {"price": {"amount": 285000.0}}, "propertyType": "flat", "operation": "sale", "size": 52.0, "rooms": 3, "bathrooms": 1, "address": "rua da Quinta do Jacinto s/n", "province": "Lisboa", "municipality": "Alc\u00e2ntara", "district": "Alvito - Quinta do Jacinto", "country": "pt", "latitude": 38.7076604, "longitude": -9.1760611, "showAddress": true, "url": "https://www.idealista.pt/imovel/33385144/", "description": "Descubra el potencial de este incre\u00edble apartamento en planta baja de 3 dormitorios en Quinta do Jacinto, ubicado en Alc\u00e1ntara. Con una variedad de caracter\u00edsticas \u00fanicas y beneficios excepcionales, esta propiedad no solo ofrece un hogar acogedor, sino que tambi\u00e9n representa una oportunidad de inversi\u00f3n verdaderamente \u00fanica y prometedora. Ubicaci\u00f3n privilegiada: Ubicado en Quinta do Jacinto, en Alc\u00e1ntara, el apartamento se encuentra en una zona en constante revalorizaci\u00f3n, con f\u00e1cil acceso a una variedad de servicios, comercios y transporte p\u00fablico. Terraza espaciosa: La gran terraza orientada al sur ofrece un espacio al aire libre perfecto para relajarse, entretenerse y disfrutar del sol. Rehabilitaci\u00f3n total en 2022: El apartamento pas\u00f3 por una profunda renovaci\u00f3n en 2022, incluyendo la rehabilitaci\u00f3n de los sistemas de agua, alcantarillado y electricidad. Esto significa que los sistemas principales est\u00e1n actualizados y en buen estado de funcionamiento, proporcionando comodidad y seguridad a los residentes. Cocina totalmente equipada: La cocina viene totalmente equipada, lo cual es conveniente para los residentes, eliminando la necesidad de invertir en electrodom\u00e9sticos y utensilios adicionales. Se vende amueblado seg\u00fan las fotograf\u00edas: La inclusi\u00f3n de muebles y equipos seg\u00fan las fotograf\u00edas, con excepci\u00f3n de algunos art\u00edculos de decoraci\u00f3n, facilita la mudanza para los nuevos propietarios, proporcionando una transici\u00f3n m\u00e1s simple y conveniente. Entrada directa desde la calle por la terraza: La entrada directa desde la calle por la terraza ofrece una comodidad adicional a los residentes, permitiendo un f\u00e1cil acceso al apartamento sin la necesidad de pasar por la entrada principal del edificio. Potencial de revalorizaci\u00f3n: La proximidad de la futura estaci\u00f3n de metro de Alc\u00e1ntara, prevista para ser completada a finales de 2026, es un punto fuerte de revalorizaci\u00f3n para la regi\u00f3n. Esto puede resultar en un aumento adicional del valor de la propiedad a lo largo del tiempo, convirti\u00e9ndola en una inversi\u00f3n atractiva. Distancias: Autob\u00fas T3B \u2013 1 minuto a pie Futura estaci\u00f3n de metro de Alc\u00e1ntara \u2013 4 minutos a pie Estaci\u00f3n de trenes Alc\u00e1ntara-Terra \u2013 6 minutos a pie Instituto Superior de Agronom\u00eda \u2013 6 minutos a pie Escuela B\u00e1sica Raul.", "hasVideo": false, "status": "good", "newDevelopment": false, "priceByArea": 5481.0, "detailedType": {"typology": "flat"}, "suggestedTexts": {"subtitle": "Alc\u00e2ntara, Lisboa", "title": "Piso en rua da Quinta do Jacinto s/n"}, "hasPlan": true, "has3DTour": false, "has360": false, "hasStaging": false, "topNewDevelopment": false, "topPlus": false}, {"propertyCode": "33385143", "thumbnail": "https://img3.idealista.pt/blur/WEB_LISTING/0/id.pro.pt.image.master/8b/db/42/243053241.jpg", "externalReference": "125771033-3", "numPhotos": 31, "price": 750000.0, "priceInfo": {"price": {"amount": 750000.0}}, "propertyType": "flat", "operation": "sale", "size": 82.0, "rooms": 2, "bathrooms": 2, "address": "rua Almirante Barroso", "province": "Lisboa", "municipality": "Arroios", "district": "S\u00e3o Jorge de Arroios", "country": "pt", "neighborhood": "Saldanha - Picoas", "latitude": 38.7299286, "longitude": -9.1433531, "showAddress": false, "url": "https://www.idealista.pt/imovel/33385143/", "description": "Descubre el lujo urbano en el exclusivo apartamento de 2 dormitorios del edificio Oasis 28, dise\u00f1ado por el reconocido Frederico Valsassina Arquitetos, en el vibrante barrio de Saldanha en Lisboa, una de las zonas m\u00e1s deseadas de Lisboa. Ubicaci\u00f3n de ensue\u00f1o: Ubicado en el coraz\u00f3n de las Avenidas Novas, este apartamento es una invitaci\u00f3n a vivir en el epicentro de la elegancia y la conveniencia. Refugio urbano exclusivo: El edificio Oasis 28, una obra maestra compuesta por 55 apartamentos, se alza majestuosamente a solo 50 metros de la emblem\u00e1tica Plaza de Saldanha. Sum\u00e9rgete en un universo de prestigio, donde empresas globales, hoteles de lujo, restaurantes exquisitos y boutiques de alta costura se mezclan armoniosamente, creando una atm\u00f3sfera de sofisticaci\u00f3n y oportunidades sin igual. Vistas impresionantes: Situado en el sexto piso, esta propiedad presenta dos suites meticulosamente dise\u00f1adas. Tanto la sala de estar como la suite principal se conectan a un amplio balc\u00f3n, que ofrece impresionantes vistas de la animada avenida principal. Pr\u00e1ctico y espacioso: Este apartamento no solo cautiva por sus detalles est\u00e9ticos, sino tambi\u00e9n por su funcionalidad. Con dos plazas de aparcamiento y un trastero, aqu\u00ed es posible encontrar el equilibrio perfecto entre lujo y practicidad. Exposici\u00f3n solar: Con una exposici\u00f3n solar privilegiada hacia el sur, este apartamento est\u00e1 ba\u00f1ado por una luz natural que crea una atm\u00f3sfera acogedora y revitalizante. Nota: Este edificio es el resultado de un proyecto singular de rehabilitaci\u00f3n urbana, en un edificio que serv\u00eda como espacio de oficinas. Con el fin de garantizar todos los criterios rigurosos de la legislaci\u00f3n actual para edificios de servicios, todos los apartamentos de 2 dormitorios con dos suites en esta vertical est\u00e1n registrados como de 1 dormitorio. Distancias: Menos de 2 minutos a pie de restaurantes; Menos de 5 minutos a pie de farmacias; Menos de 5 minutos a pie de supermercados; Menos de 5 minutos a pie del centro comercial; 10 minutos en coche de la Baixa de Lisboa; De 10 a 15 minutos en coche de hospitales y centros de salud; De 10 a 15 minutos en coche de las escuelas; 15 minutos en coche del Aeropuerto Internacional de Lisboa.", "hasVideo": false, "status": "good", "newDevelopment": false, "priceByArea": 9146.0, "detailedType": {"typology": "flat"}, "suggestedTexts": {"subtitle": "Saldanha - Picoas, Lisboa", "title": "Piso en rua Almirante Barroso"}, "hasPlan": false, "has3DTour": false, "has360": false, "hasStaging": false, "topNewDevelopment": false, "topPlus": false}, {"propertyCode": "33385142", "thumbnail": "https://img3.idealista.pt/blur/WEB_LISTING/0/id.pro.pt.image.master/fb/87/69/243053178.jpg", "externalReference": "125771033-2", "numPhotos": 50, "price": 1650000.0, "priceInfo": {"price": {"amount": 1650000.0}}, "propertyType": "flat", "operation": "sale", "size": 230.0, "rooms": 4, "bathrooms": 3, "address": "rua Doutor Silva Teles", "province": "Lisboa", "municipality": "Avenidas Novas", "district": "Gulbenkian - Pra\u00e7a Espanha", "country": "pt", "latitude": 38.7371391, "longitude": -9.1543785, "showAddress": false, "url": "https://www.idealista.pt/imovel/33385142/", "hasVideo": false, "status": "good", "newDevelopment": false, "priceByArea": 7174.0, "detailedType": {"typology": "flat"}, "suggestedTexts": {"subtitle": "Avenidas Novas, Lisboa", "title": "Piso en rua Doutor Silva Teles"}, "hasPlan": false, "has3DTour": false, "has360": false, "hasStaging": false, "topNewDevelopment": false, "topPlus": false}, {"propertyCode": "33308679", "thumbnail": "https://img3.idealista.pt/blur/WEB_LISTING/0/id.pro.pt.image.master/70/b9/9f/240007716.jpg", "externalReference": "126321061-65", "numPhotos": 27, "price": 750000.0, "priceInfo": {"price": {"amount": 750000.0}}, "propertyType": "flat", "operation": "sale", "size": 139.0, "rooms": 5, "bathrooms": 2, "address": "rua dos Correeiros", "province": "Lisboa", "municipality": "Santa Maria Maior", "district": "Baixa", "country": "pt", "latitude": 38.7096532, "longitude": -9.1394742, "showAddress": false, "url": "https://www.idealista.pt/imovel/33308679/", "hasVideo": true, "status": "good", "newDevelopment": false, "priceByArea": 5396.0, "detailedType": {"typology": "flat"}, "suggestedTexts": {"subtitle": "Santa Maria Maior, Lisboa", "title": "Piso en rua dos Correeiros"}, "hasPlan": false, "has3DTour": false, "has360": false, "hasStaging": false, "topNewDevelopment": false, "topPlus": false}, {"propertyCode": "33385034", "thumbnail": "https://img3.idealista.pt/blur/WEB_LISTING/0/id.pro.pt.image.master/1d/4e/33/243051135.jpg", "externalReference": "122181510-5", "numPhotos": 42, "price": 350000.0, "priceInfo": {"price": {"amount": 350000.0}}, "propertyType": "flat", "operation": "sale", "size": 50.0, "rooms": 2, "bathrooms": 2, "address": "Alfama - S\u00e9", "province": "Lisboa", "municipality": "Santa Maria Maior", "district": "Alfama - S\u00e9", "country": "pt", "latitude": 38.7141192, "longitude": -9.1252899, "showAddress": false, "url": "https://www.idealista.pt/imovel/33385034/", "description": "Excelente oportunidad de inversi\u00f3n con retorno lucrativo y garantizado, en una de las zonas m\u00e1s prestigiosas de Lisboa. Este apartamento T2 es completamente nuevo. Ha sido recientemente renovado y decorado por la arquitecta Diana Horta, dando como resultado un espacio moderno y elegante. El apartamento est\u00e1 completamente amueblado y tiene dos ba\u00f1os igualmente modernos y elegantes. Es perfecto para aquellos que valoran la comodidad y la practicidad. La vista al r\u00edo es impresionante y la ubicaci\u00f3n es simplemente ideal, ya que est\u00e1 a solo 5 minutos a pie de la estaci\u00f3n de metro m\u00e1s cercana y de la explanada junto al r\u00edo, donde podr\u00e1 disfrutar de momentos agradables. Adem\u00e1s, el apartamento est\u00e1 convenientemente ubicado cerca de todos los servicios y comercios. Tenemos un servicio innovador, a medida, Your Home: Servicio de mudanzas y almacenamiento temporal; Proyecto de Decoraci\u00f3n de Interiores; Peque\u00f1as remodelaciones en el contexto del proyecto de dise\u00f1o; Servicio de Limpieza del inmueble.", "hasVideo": false, "status": "good", "newDevelopment": false, "priceByArea": 7000.0, "detailedType": {"typology": "flat"}, "suggestedTexts": {"subtitle": "Santa Maria Maior, Lisboa", "title": "Piso"}, "hasPlan": true, "has3DTour": false, "has360": false, "hasStaging": false, "topNewDevelopment": false, "topPlus": false}, {"propertyCode": "33384986", "thumbnail": "https://img3.idealista.pt/blur/WEB_LISTING/0/id.pro.pt.image.master/8c/1b/3c/243050095.jpg", "externalReference": "123171251-88", "numPhotos": 19, "price": 290000.0, "priceInfo": {"price": {"amount": 290000.0}}, "propertyType": "studio", "operation": "sale", "size": 46.0, "rooms": 0, "bathrooms": 1, "address": "rua Gilberto Rola s/n", "province": "Lisboa", "municipality": "Estrela", "district": "Alc\u00e2ntara", "country": "pt", "latitude": 38.7055302, "longitude": -9.1725873, "showAddress": true, "url": "https://www.idealista.pt/imovel/33384986/", "hasVideo": false, "status": "good", "newDevelopment": false, "priceByArea": 6304.0, "detailedType": {"typology": "flat", "subTypology": "studio"}, "suggestedTexts": {"subtitle": "Estrela, Lisboa", "title": "T0 en rua Gilberto Rola s/n"}, "hasPlan": true, "has3DTour": false, "has360": false, "hasStaging": false, "topNewDevelopment": false, "topPlus": false}], "total": 12205, "totalPages": 245, "actualPage": 28, "itemsPerPage": 50, "numPaginations": 0, "summary": ["Comprar", "Viviendas", "Lisboa", "Todos los precios", "Todos los tama\u00f1os"], "filter": {"locationName": "Lisboa"}, "alertName": "Viviendas en Lisboa", "totalAppliedFilters": 0, "lowerRangePosition": 1350, "paginable": true, "upperRangePosition": 1400}